README.rst
check_sentry_messages.py
setup.py
nagios_sentry/__init__.py
nagios_sentry.egg-info/PKG-INFO
nagios_sentry.egg-info/SOURCES.txt
nagios_sentry.egg-info/dependency_links.txt
nagios_sentry.egg-info/not-zip-safe
nagios_sentry.egg-info/requires.txt
nagios_sentry.egg-info/top_level.txt
nagios_sentry/management/__init__.py
nagios_sentry/management/commands/__init__.py
nagios_sentry/management/commands/count_of_groups.py
nagios_sentry/management/commands/count_of_messages.py