Metadata-Version: 1.1
Name: nagios-sentry
Version: 0.3.1
Summary: Plugin for Nagios, which check a count of messages in Sentry
Home-page: http://github.com/adw0rd/nagios-sentry
Author: Mikhail Andreev
Author-email: x11org@gmail.com
License: BSD
Keywords: nagios,sentry
Platform: UNKNOWN
Classifier: Environment :: Web Environment
Classifier: Programming Language :: Python
Classifier: License :: OSI Approved :: BSD License
Classifier: Topic :: Software Development :: Libraries :: Application Frameworks
Classifier: Topic :: Software Development :: Libraries :: Python Modules
